<?xml version="1.0" encoding="UTF-8"?>
<slot-configurations xmlns="http://www.demandware.com/xml/impex/slot/2008-09-08">
    <slot-configuration slot-id="cart-recommendations-m" context="global" configuration-id="algolia-frequently-bought-together" default="true" assigned-to-site="true">
        <template>slots/product/frequently-bought-together.isml</template>
        <enabled-flag>true</enabled-flag>
        <content>
            <products/>
        </content>
    </slot-configuration>

    <slot-configuration slot-id="product-recommendations-m" context="global" configuration-id="algolia-frequently-bought-together-pdp" default="true" assigned-to-site="true">
        <template>slots/product/frequently-bought-together.isml</template>
        <enabled-flag>true</enabled-flag>
        <content>
            <products/>
        </content>
    </slot-configuration>

    <slot-configuration slot-id="algolia-home-products" context="global" configuration-id="algolia-home-products" default="true" assigned-to-site="true">
        <template>slots/product/trending-items.isml</template>
        <enabled-flag>true</enabled-flag>
        <content>
            <products/>
        </content>
    </slot-configuration>
</slot-configurations>
